rosu_pp_py-3.1.0.dist-info/METADATA
rosu_pp_py-3.1.0.dist-info/WHEEL
rosu_pp_py-3.1.0.dist-info/licenses/LICENSE
rosu_pp_py.libs/libgcc_s-e52197c3.so.1
rosu_pp_py/__init__.py
rosu_pp_py/__init__.pyi
rosu_pp_py/py.typed
rosu_pp_py/rosu_pp_py.cpython-310-aarch64-linux-gnu.so
rosu_pp_py-3.1.0.dist-info/RECORD
