Metadata-Version: 2.4
Name: rosu-pp-py
Version: 3.1.0
Classifier: Intended Audience :: Developers
Classifier: License :: OSI Approved :: MIT License
Classifier: Operating System :: OS Independent
Classifier: Programming Language :: Rust
Classifier: Programming Language :: Python :: Implementation :: CPython
Classifier: Programming Language :: Python :: Implementation :: PyPy
License-File: LICENSE
Summary: Difficulty and performance calculation for osu!
Keywords: osu,pp,stars,performance,difficulty
Author: Max Ohn <ohn.m@hotmail.de>
Author-email: Max Ohn <ohn.m@hotmail.de>
License: MIT
Requires-Python: >=3.7
Project-URL: Source Code, https://github.com/MaxOhn/rosu-pp-py
